[
  {
    "name": "Алракис",
    "id": "mu. Dra"
  },
  {
    "name": "Гельветиос",
    "id": "51 Peg"
  },
  {
    "name": "Тайи",
    "id": "8 Dra"
  },
  {
    "name": "Сервантес",
    "id": "mu. Ara"
  },
  {
    "name": "Гуниибуу",
    "id": "36 Oph"
  },
  {
    "name": "Чалаван",
    "id": "47 UMa"
  },
  {
    "name": "Диадема",
    "id": "alf Com"
  },
  {
    "name": "Теребелл",
    "id": "ome Sgr"
  },
  {
    "name": "Альсафи",
    "id": "sig Dra"
  },
  {
    "name": "Алюла Австралис",
    "id": "ksi UMa"
  },
  {
    "name": "Курхах",
    "id": "ksi Cep"
  },
  {
    "name": "Хара",
    "id": "bet CVn"
  },
  {
    "name": "Сюаньгэ",
    "id": "lam Boo"
  },
  {
    "name": "Титавин",
    "id": "ups And"
  },
  {
    "name": "Сирма",
    "id": "iot Vir"
  },
  {
    "name": "Альхиба",
    "id": "alf Crv"
  },
  {
    "name": "Нусакан",
    "id": "bet CrB"
  },
  {
    "name": "Далим",
    "id": "alf For"
  },
  {
    "name": "Преципуя",
    "id": "46 LMi"
  },
  {
    "name": "Ран",
    "id": "eps Eri"
  },
  {
    "name": "Альшаин",
    "id": "bet Aql"
  },
  {
    "name": "Ротанев",
    "id": "bet Del"
  },
  {
    "name": "Завиява",
    "id": "bet Vir"
  },
  {
    "name": "Каффальджидхма",
    "id": "gam Cet"
  },
  {
    "name": "Васат",
    "id": "del Gem"
  },
  {
    "name": "Бихам",
    "id": "tet Peg"
  },
  {
    "name": "Садалбари",
    "id": "mu. Peg"
  },
  {
    "name": "Ахирд",
    "id": "eta Cas"
  },
  {
    "name": "Поррима",
    "id": "gam Vir"
  },
  {
    "name": "Моталлах",
    "id": "alf Tri"
  },
  {
    "name": "Хезе",
    "id": "zet Vir"
  },
  {
    "name": "Альзирр",
    "id": "ksi Gem"
  },
  {
    "name": "Денеб Окаб",
    "id": "del Aql"
  },
  {
    "name": "Граффиас",
    "id": "eta Sco"
  },
  {
    "name": "Мегрец",
    "id": "del UMa"
  },
  {
    "name": "Эдасих",
    "id": "iot Dra"
  },
  {
    "name": "Йед Постериор",
    "id": "eps Oph"
  },
  {
    "name": "Эрраи",
    "id": "gam Cep"
  },
  {
    "name": "Аль Хауд",
    "id": "tet UMa"
  },
  {
    "name": "Талитха",
    "id": "iot UMa"
  },
  {
    "name": "Сарин",
    "id": "del Her"
  },
  {
    "name": "Вазн",
    "id": "bet Col"
  },
  {
    "name": "Альтаис",
    "id": "del Dra"
  },
  {
    "name": "Сегинус",
    "id": "gam Boo"
  },
  {
    "name": "Ока",
    "id": "zet Aql"
  },
  {
    "name": "Альгора",
    "id": "del Crv"
  },
  {
    "name": "Виндемиатрикс",
    "id": "eps Vir"
  },
  {
    "name": "Денеб Алгеди",
    "id": "del Cap"
  },
  {
    "name": "Турейс",
    "id": "rho Pup"
  },
  {
    "name": "Каус Бореалис",
    "id": "lam Sgr"
  },
  {
    "name": "Курса",
    "id": "bet Eri"
  },
  {
    "name": "Цебальрай",
    "id": "bet Oph"
  },
  {
    "name": "Зубен эль Генуби",
    "id": "alf02 Lib"
  },
  {
    "name": "Athebyne",
    "id": "eta Dra"
  },
  {
    "name": "Шератан",
    "id": "bet Ari"
  },
  {
    "name": "Муфрид",
    "id": "eta Boo"
  },
  {
    "name": "Рукба",
    "id": "del Cas"
  },
  {
    "name": "Унукалхай",
    "id": "alf Ser"
  },
  {
    "name": "Асцелла",
    "id": "zet Sgr"
  },
  {
    "name": "Зосма",
    "id": "del Leo"
  },
  {
    "name": "Дженах",
    "id": "eps Cyg"
  },
  {
    "name": "Альдерамин",
    "id": "alf Cep"
  },
  {
    "name": "Сабик",
    "id": "eta Oph"
  },
  {
    "name": "Фекда",
    "id": "gam UMa"
  },
  {
    "name": "Анкаа",
    "id": "alf Phe"
  },
  {
    "name": "Мерак",
    "id": "bet UMa"
  },
  {
    "name": "Лараваг",
    "id": "eps Sco"
  },
  {
    "name": "Каф",
    "id": "bet Cas"
  },
  {
    "name": "Мицар",
    "id": "zet UMa"
  },
  {
    "name": "Альфекка",
    "id": "alf CrB"
  },
  {
    "name": "Денебола",
    "id": "bet Leo"
  },
  {
    "name": "Алголь",
    "id": "bet Per"
  },
  {
    "name": "Расальхаг",
    "id": "alf Oph"
  },
  {
    "name": "Альферац",
    "id": "alf And"
  },
  {
    "name": "Менкент",
    "id": "tet Cen"
  },
  {
    "name": "Дифда",
    "id": "bet Cet"
  },
  {
    "name": "Хамаль",
    "id": "alf Ari"
  },
  {
    "name": "Альсефина",
    "id": "del Vel"
  },
  {
    "name": "Кастор",
    "id": "alf Gem"
  },
  {
    "name": "Альхена",
    "id": "gam Gem"
  },
  {
    "name": "Менкалинан",
    "id": "bet Aur"
  },
  {
    "name": "Алкаид",
    "id": "eta UMa"
  },
  {
    "name": "Алиот",
    "id": "eps UMa"
  },
  {
    "name": "Альнаир",
    "id": "alf Gru"
  },
  {
    "name": "Гакрукс",
    "id": "gam Cru"
  },
  {
    "name": "Регул",
    "id": "alf Leo"
  },
  {
    "name": "Толиман",
    "id": "alf Cen"
  },
  {
    "name": "Фомальгаут",
    "id": "alf PsA"
  },
  {
    "name": "Поллукс",
    "id": "bet Gem"
  },
  {
    "name": "Альдебаран",
    "id": "alf Tau"
  },
  {
    "name": "Альтаир",
    "id": "alf Aql"
  },
  {
    "name": "Процион",
    "id": "alf CMi"
  },
  {
    "name": "Капелла",
    "id": "alf Aur"
  },
  {
    "name": "Вега",
    "id": "alf Lyr"
  },
  {
    "name": "Ригиль Кентаврус",
    "id": "alf Cen"
  },
  {
    "name": "Арктур",
    "id": "alf Boo"
  },
  {
    "name": "Сириус",
    "id": "alf CMa"
  }
]